{"모욕": 2, "욕설": 0, "외설": 0, "폭력위협/범죄조장": 0, "성혐오": 0, "연령": 0, "인종/지역": 2, "장애": 0, "종교": 2, "정치성향": 0, "직업": 0, "1단계Y/N": "Y", "2-1단계Y/N": "Y", "2-2단계Y/N": "Y", "문장": "말이 한국에 협력한 애들이지 막말로 ''친일파 앞잡이'''같은것들인데 ''지조국 등지'''고 ''적국에 붙어'''먹어서 ''자국민 팔아'''넘기더애들이 이땅에 들어와서 아이고 고마운 코리아 착하게 살께요 하겠냐 무슬림들이 왜자꾸 한국에 오려는지 모르나 걔들은 그냥 작고 잘사는 나라를 갖고싶어하는거야 한국으로 망명하겠다는 무슬림들이 한국을 갖게 해달라고 기도하고 들어와서도 우리에 동화되기는커녕 ''온갖범죄 다저지르'''고  지들 게토 만들어서 지들식 나라 만드는 애들인데 유럽 작은나라에선 지들끼리 무장자경단 만들어서 원주민들 한테 이슬람 율법따르라고 순찰까지도는데", "대상하이라이트": "말이 한국에 협력한 애들이지 막말로 ''친일파 앞잡이'''같은것들인데 지조국 등지고 적국에 붙어먹어서 자국민 팔아넘기더애들이 이땅에 들어와서 아이고 고마운 코리아 착하게 살께요 하겠냐 ''무슬림'''들이 왜자꾸 한국에 오려는지 모르나 걔들은 그냥 작고 잘사는 나라를 갖고싶어하는거야 한국으로 망명하겠다는 ''무슬림'''들이 한국을 갖게 해달라고 기도하고 들어와서도 우리에 동화되기는커녕 온갖범죄 다저지르고  지들 ''게토''' 만들어서 지들식 나라 만드는 애들인데 유럽 작은나라에선 지들끼리 ''무장자경단''' 만들어서 원주민들 한테 ''이슬람''' 율법따르라고 순찰까지도는데", "인종/지역Y/N": "Y", "종교Y/N": "Y", "혐오 클래스": "Y", "특정 집단": "N", "그 외": "N"}