{"모욕": 3, "욕설": 2, "외설": 0, "폭력위협/범죄조장": 0, "성혐오": 0, "연령": 0, "인종/지역": 0, "장애": 0, "종교": 0, "정치성향": 0, "직업": 0, "1단계Y/N": "Y", "2-1단계Y/N": "Y", "2-2단계Y/N": "Y", "문장": "별 ''쓰레기'''들이 ''지랄'''하네. WHO가 뭐하는 곳인데 ''멍청한''' 것들이…주제넘게 하라 하지마라거리네~ 해준 것도 없는 ''쓰레기'''들이~ 부스터샷 안 해서 이스라엘 확진자 늘어나고 사망자 생기면 뭐 책임이라도 져주게??? 벌 ''똥같'''은 ''넘'''들이…그냥 WHO ''없애저리면 좋'''겠다!", "대상하이라이트": "별 쓰레기들이 지랄하네. ''WHO'''가 뭐하는 곳인데 멍청한 것들이…주제넘게 하라 하지마라거리네~ 해준 것도 없는 쓰레기들이~ 부스터샷 안 해서 이스라엘 확진자 늘어나고 사망자 생기면 뭐 책임이라도 져주게??? 벌 똥같은 넘들이…그냥 ''WHO''' 없애저리면 좋겠다!", "혐오 클래스": "N", "특정 집단": "Y", "그 외": "N"}