{"모욕": 2, "욕설": 2, "외설": 0, "폭력위협/범죄조장": 0, "성혐오": 0, "연령": 0, "인종/지역": 0, "장애": 0, "종교": 0, "정치성향": 2, "직업": 0, "1단계Y/N": "Y", "2-1단계Y/N": "Y", "2-2단계Y/N": "Y", "문장": "1941년 12월 7일에도 그렇게 깝치던 일본군이 있었지..지금 #@이름# 시계는 그 시간에 멈춰있다..전체주의 국수주의 침략주의 안하무인 독선 오만 거기에 무능까지..일본군에 점령당해 다 죽어 가던 #@이름# 누가 구했냐?? 1944년일본군의 대륙 관통 작전때 #@이름# 직계 정예사단 갈려 나가지만 안았어도 #@이름# 공산당 없었다..1946년 봉림과 장춘에서 수백만 자국민 학살하고 집권한 ''악마''' ''새퀴'''들이..정말 ''역겹'''다..#@이름# 보고 있냐??", "대상하이라이트": "1941년 12월 7일에도 그렇게 깝치던 일본군이 있었지..지금 ''#@이름#''' 시계는 그 시간에 멈춰있다..전체주의 국수주의 침략주의 안하무인 독선 오만 거기에 무능까지..일본군에 점령당해 다 죽어 가던 #@이름# 누가 구했냐?? 1944년일본군의 대륙 관통 작전때 #@이름# 직계 정예사단 갈려 나가지만 안았어도 ''#@이름#''' 공산당 없었다..1946년 봉림과 장춘에서 수백만 자국민 학살하고 집권한 ''악마 새퀴'''들이..정말 역겹다..''#@이름#''' 보고 있냐??", "정치성향Y/N": "Y", "혐오 클래스": "Y", "특정 집단": "N", "그 외": "N"}