{"모욕": 2, "욕설": 0, "외설": 0, "폭력위협/범죄조장": 0, "성혐오": 1, "연령": 0, "인종/지역": 0, "장애": 0, "종교": 0, "정치성향": 0, "직업": 0, "1단계Y/N": "Y", "2-1단계Y/N": "Y", "2-2단계Y/N": "N", "문장": "아니 안산을 지키려는 정의의 사도들이 왜 #@이름#, 어거돈 피해자는 지켜주고 못하고 입을 다물고 계셨을까? 그리고 #@이름# 자살때 남자들이 악플 달아서 죽었다고 남자가 범죄자라 공격하다 악플의 90%가 여자인게 밝혀지니까 꿀먹은 벙어리 조용. ㅋㅋ", "대상하이라이트": "아니 ''안산을 지키려는 정의의 사도'''들이 왜 #@이름#, 어거돈 피해자는 지켜주고 못하고 입을 다물고 계셨을까? 그리고 #@이름# 자살때 남자들이 악플 달아서 죽었다고 남자가 범죄자라 공격하다 악플의 90%가 여자인게 밝혀지니까 꿀먹은 벙어리 조용. ㅋㅋ", "성혐오Y/N": "Y", "혐오 클래스": "Y", "특정 집단": "N", "그 외": "N"}