{"모욕": 1, "욕설": 0, "외설": 0, "폭력위협/범죄조장": 0, "성혐오": 0, "연령": 0, "인종/지역": 0, "장애": 0, "종교": 0, "정치성향": 2, "직업": 0, "1단계Y/N": "Y", "2-1단계Y/N": "Y", "2-2단계Y/N": "Y", "문장": "받아오지도 못하는 모더나를 거론하는건 위험하지 않나? 더구나 ''문빠'''들이 싫어하는 조중동 아닌가! 아스트라 문제생기니 아스트라 버리고 새로준비해서 접종이늦어진 일본에 뒤진것 옛날이고 이젠 OECD에서 접종뫈료율 꼴찌라던데, 더구나 6월에 아스트라 겨우 맞은 사람들 *차접종 시작인데 또 1주 지연된다고하던데. 그래서일까 요즘 백신 접종율에대해서 일본은 거론도 못하고, *차접종율은 말도 안하는게 요즘 K방역의 현실이지. 거론되는것조차 부끄러은 K방역은 정치에 이용된 방역으로 역사에 기록될것이다", "대상하이라이트": "받아오지도 못하는 모더나를 거론하는건 위험하지 않나? 더구나 ''문빠'''들이 싫어하는 조중동 아닌가! 아스트라 문제생기니 아스트라 버리고 새로준비해서 접종이늦어진 일본에 뒤진것 옛날이고 이젠 OECD에서 접종뫈료율 꼴찌라던데, 더구나 6월에 아스트라 겨우 맞은 사람들 *차접종 시작인데 또 1주 지연된다고하던데. 그래서일까 요즘 백신 접종율에대해서 일본은 거론도 못하고, *차접종율은 말도 안하는게 요즘 K방역의 현실이지. 거론되는것조차 부끄러은 K방역은 정치에 이용된 방역으로 역사에 기록될것이다", "정치성향Y/N": "Y", "혐오 클래스": "Y", "특정 집단": "N", "그 외": "N"}