{"모욕": 1, "욕설": 0, "외설": 0, "폭력위협/범죄조장": 0, "성혐오": 0, "연령": 0, "인종/지역": 0, "장애": 0, "종교": 0, "정치성향": 2, "직업": 0, "1단계Y/N": "Y", "2-1단계Y/N": "Y", "2-2단계Y/N": "Y", "문장": "''대깨'''들아 못하는 베트남이랑 비교를 하지 말고...성공적으로 위드 코로나 진행 하고 있는 싱가포르 하고 비교를 해봐라. 싱가포르는 백신 제대로 구해와서 백신 *차 접종 6~70% 끝내고...위드 코로나 제대로 하고 있으니까 말야. 우리 국민들이 원하는 것이 싱가포르 모델이다. 위드 코로나 이야길 하면 영국 들먹이지 말고. 우리랑 영국이랑은 민족성이 틀리잖아. 위드 코로나 하면서도 방역 위반을 하는 경우 제대로 된 처벌도 같이 하는 싱가포르 모델을 국민들이 원하고 있는데...백신도 못 구하고 있는데", "대상하이라이트": "''대깨'''들아 못하는 베트남이랑 비교를 하지 말고...성공적으로 위드 코로나 진행 하고 있는 싱가포르 하고 비교를 해봐라. 싱가포르는 백신 제대로 구해와서 백신 *차 접종 6~70% 끝내고...위드 코로나 제대로 하고 있으니까 말야. 우리 국민들이 원하는 것이 싱가포르 모델이다. 위드 코로나 이야길 하면 영국 들먹이지 말고. 우리랑 영국이랑은 민족성이 틀리잖아. 위드 코로나 하면서도 방역 위반을 하는 경우 제대로 된 처벌도 같이 하는 싱가포르 모델을 국민들이 원하고 있는데...백신도 못 구하고 있는데", "정치성향Y/N": "Y", "혐오 클래스": "Y", "특정 집단": "N", "그 외": "N"}