{"모욕": 2, "욕설": 0, "외설": 0, "폭력위협/범죄조장": 0, "성혐오": 0, "연령": 0, "인종/지역": 2, "장애": 0, "종교": 0, "정치성향": 0, "직업": 0, "1단계Y/N": "Y", "2-1단계Y/N": "Y", "2-2단계Y/N": "Y", "문장": "이건 좀 아니지 않나?  #@이름# ''사살'''로 목적 달성했으니 철군했다고 해놓고,  지금은 911테러를 빌미로 자금을 동결한다고?  탈레반에게 ''미쳐 날뛰'''라고 ''부추기'''는 거 아닌가?  미국의 대외정책이 심각한 ''갈짓자를 그리'''네.", "대상하이라이트": "이건 좀 아니지 않나?  #@이름# 사살로 목적 달성했으니 철군했다고 해놓고,  지금은 911테러를 빌미로 자금을 동결한다고?  ''탈레반'''에게 미쳐 날뛰라고 부추기는 거 아닌가?  ''미국의 대외정책'''이 심각한 갈짓자를 그리네.", "인종/지역Y/N": "Y", "혐오 클래스": "Y", "특정 집단": "N", "그 외": "N"}