{"모욕": 2, "욕설": 0, "외설": 0, "폭력위협/범죄조장": 0, "성혐오": 0, "연령": 0, "인종/지역": 0, "장애": 0, "종교": 0, "정치성향": 2, "직업": 0, "1단계Y/N": "Y", "2-1단계Y/N": "Y", "2-2단계Y/N": "Y", "문장": "뮐알아야 면장''질'''이라도 하지. ''무식'''한 것도 자랑이라고 자화지찬하는 ''또라이''' ''짓'''도 한두번이지.코로나 사태이후 백신 갖고 몇번이나 국민들을 상대로 ''사기를 치'''면서 ''뻔뻔하'''게 굴었는데도 좋다는 사이비종교에 빠진 ''문빠'''와 ''좌빨'''들이 ''판치'''는 한 어쩔 수 없을 것같다.", "대상하이라이트": "뮐알아야 면장질이라도 하지. 무식한 것도 자랑이라고 자화지찬하는 또라이 짓도 한두번이지.코로나 사태이후 백신 갖고 몇번이나 국민들을 상대로 사기를 치면서 뻔뻔하게 굴었는데도 좋다는 사이비종교에 빠진 ''문빠'''와 ''좌빨'''들이 판치는 한 어쩔 수 없을 것같다.", "정치성향Y/N": "Y", "혐오 클래스": "Y", "특정 집단": "Y", "그 외": "N"}