{"모욕": 2, "욕설": 2, "외설": 0, "폭력위협/범죄조장": 0, "성혐오": 0, "연령": 0, "인종/지역": 0, "장애": 0, "종교": 0, "정치성향": 0, "직업": 0, "1단계Y/N": "Y", "2-1단계Y/N": "Y", "2-2단계Y/N": "Y", "문장": "#@이름#님 제발 사과 표현좀 해주세요..''특등머저리''' 체면이 말이 아닙니다..부탁합니다..제발 공급 잘못해서 미안하단 말좀 해주세요..우리 삶은 #@이름#님이 앙천대소하며 ''실성할'''까 두렵습니다...#@이름#님 ''미개한''' 국민들 속일 수 있도록..사과한마디만 부탁합니다..", "대상하이라이트": "''#@이름#'''님 제발 사과 표현좀 해주세요..특등머저리 체면이 말이 아닙니다..부탁합니다..제발 공급 잘못해서 미안하단 말좀 해주세요..우리 삶은 ''#@이름#'''님이 앙천대소하며 실성할까 두렵습니다...''#@이름#'''님 미개한 ''국민'''들 속일 수 있도록..사과한마디만 부탁합니다..", "혐오 클래스": "N", "특정 집단": "Y", "그 외": "Y"}