{"모욕": 2, "욕설": 0, "외설": 0, "폭력위협/범죄조장": 0, "성혐오": 0, "연령": 0, "인종/지역": 2, "장애": 0, "종교": 0, "정치성향": 0, "직업": 0, "1단계Y/N": "Y", "2-1단계Y/N": "Y", "2-2단계Y/N": "Y", "문장": "일부 악질 ''토왜'''들이 ''조센징'''은 그따위밖에 안된다느니 범가죽이 벗겨져 내려왔다느니 ''아가리'''로 온갖 ''설사똥'''을 싸대는데 일부러 이런 무더위중에 대회를 열면서 무더위 적응못하는 타국선수들은 골판지에서 재우고 지들은 고급호텔에서 묵으며 따낸 올림픽 금메달 그거 다 한순간이야. 이제 니들을 기다리고 있는 것은 기나긴 고통과 죽음의 확진자 증가와 빚더미에 짓눌린 상처뿐인 영광뿐이다. 격하게 축하한다.", "대상하이라이트": "일부 악질 ''토왜'''들이 조센징은 그따위밖에 안된다느니 범가죽이 벗겨져 내려왔다느니 아가리로 온갖 설사똥을 싸대는데 일부러 이런 무더위중에 대회를 열면서 무더위 적응못하는 타국선수들은 골판지에서 재우고 지들은 고급호텔에서 묵으며 따낸 올림픽 금메달 그거 다 한순간이야. 이제 니들을 기다리고 있는 것은 기나긴 고통과 죽음의 확진자 증가와 빚더미에 짓눌린 상처뿐인 영광뿐이다. 격하게 축하한다.", "인종/지역Y/N": "Y", "혐오 클래스": "Y", "특정 집단": "N", "그 외": "N"}