{"모욕": 2, "욕설": 1, "외설": 0, "폭력위협/범죄조장": 0, "성혐오": 0, "연령": 0, "인종/지역": 0, "장애": 0, "종교": 0, "정치성향": 0, "직업": 0, "1단계Y/N": "Y", "2-1단계Y/N": "Y", "2-2단계Y/N": "Y", "문장": "허위정보가 아니라 맞는 얘기다.이 사람들 잘하고 있다.  역으로 코로나와 백신이 ''허구'''다!! 세계정부주의자와 부자들이 만들어낸. ''개''' ''돼지'''들을 줄이고 만들고  ''지배'''하려고 !  #@이름#과 그 일당들은 올커니 코로나를 빙자해 만나는 것을 제한하며 정치방역 하고 지멋대로 교회(정적 전광훈 제거목적, 주사파 공산주의자들의 교회말살, 여론조작 선동등)를 폐쇄하고. 숫자는 ''여론조작'''처럼 ''거짓'''으로 ''지멋대로 조작'''하는 것으로 보인다  주위에 코로나 걸려서 죽어가는 것을 본 사람이 있는가??  ''효능도 없'''는 백신 맞아 죽는 사람이 아니라??", "대상하이라이트": "허위정보가 아니라 맞는 얘기다.이 사람들 잘하고 있다.  역으로 코로나와 ''백신'''이 허구다!! ''세계정부주의자'''와 ''부자'''들이 만들어낸. 개 돼지들을 줄이고 만들고  지배하려고 !  ''#@이름#'''과 그 일당들은 올커니 코로나를 빙자해 만나는 것을 제한하며 ''정치방역''' 하고 지멋대로 교회(정적 전광훈 제거목적, 주사파 공산주의자들의 교회말살, 여론조작 선동등)를 폐쇄하고. 숫자는 여론조작처럼 거짓으로 지멋대로 조작하는 것으로 보인다  주위에 코로나 걸려서 죽어가는 것을 본 사람이 있는가??  효능도 없는 ''백신''' 맞아 죽는 사람이 아니라??", "혐오 클래스": "N", "특정 집단": "Y", "그 외": "Y"}